udfc/__init__.py
udfc/main.py
udfc/udfc.py
udfc-0.3.dist-info/METADATA
udfc-0.3.dist-info/WHEEL
udfc-0.3.dist-info/entry_points.txt
udfc-0.3.dist-info/top_level.txt
udfc-0.3.dist-info/RECORD
